kinetic_sdk_v2/__init__.py
kinetic_sdk_v2/generated/.gitignore
kinetic_sdk_v2/generated/.gitlab-ci.yml
kinetic_sdk_v2/generated/.openapi-generator/FILES
kinetic_sdk_v2/generated/.openapi-generator/VERSION
kinetic_sdk_v2/generated/.openapi-generator-ignore
kinetic_sdk_v2/generated/.travis.yml
kinetic_sdk_v2/generated/client/__init__.py
kinetic_sdk_v2/generated/client/api/__init__.py
kinetic_sdk_v2/generated/client/api/account_api.py
kinetic_sdk_v2/generated/client/api/airdrop_api.py
kinetic_sdk_v2/generated/client/api/app_api.py
kinetic_sdk_v2/generated/client/api/transaction_api.py
kinetic_sdk_v2/generated/client/api_client.py
kinetic_sdk_v2/generated/client/apis/__init__.py
kinetic_sdk_v2/generated/client/configuration.py
kinetic_sdk_v2/generated/client/exceptions.py
kinetic_sdk_v2/generated/client/model/__init__.py
kinetic_sdk_v2/generated/client/model/app_config.py
kinetic_sdk_v2/generated/client/model/app_config_api.py
kinetic_sdk_v2/generated/client/model/app_config_app.py
kinetic_sdk_v2/generated/client/model/app_config_cluster.py
kinetic_sdk_v2/generated/client/model/app_config_environment.py
kinetic_sdk_v2/generated/client/model/app_config_mint.py
kinetic_sdk_v2/generated/client/model/app_health.py
kinetic_sdk_v2/generated/client/model/balance_response.py
kinetic_sdk_v2/generated/client/model/balance_token.py
kinetic_sdk_v2/generated/client/model/cluster_type.py
kinetic_sdk_v2/generated/client/model/commitment.py
kinetic_sdk_v2/generated/client/model/confirmed_signature_info.py
kinetic_sdk_v2/generated/client/model/confirmed_transaction_meta.py
kinetic_sdk_v2/generated/client/model/create_account_request.py
kinetic_sdk_v2/generated/client/model/get_transaction_response.py
kinetic_sdk_v2/generated/client/model/history_response.py
kinetic_sdk_v2/generated/client/model/latest_blockhash_response.py
kinetic_sdk_v2/generated/client/model/make_transfer_request.py
kinetic_sdk_v2/generated/client/model/minimum_rent_exemption_balance_response.py
kinetic_sdk_v2-1.0.1.dist-info/WHEEL
kinetic_sdk_v2-1.0.1.dist-info/METADATA
kinetic_sdk_v2-1.0.1.dist-info/RECORD
